TshetUinhEncoder/__init__.py
TshetUinhEncoder/_母對應的標準等.py
TshetUinhEncoder/常量.py
TshetUinhEncoder/音韻地位.py
TshetUinhEncoder/韻鏡位置.py
TshetUinhEncoder/工具/__init__.py
TshetUinhEncoder/工具/反切.py
TshetUinhEncoder/工具/音韻地位到韻鏡位置.py
TshetUinhEncoder/工具/音韻屬性到韻鏡位置們.py
TshetUinhEncoder/工具/韻鏡位置到音韻地位.py
TshetUinhEncoder/轉換/__init__.py
TshetUinhEncoder/轉換/母到清濁.py
TshetUinhEncoder/轉換/母到組.py
TshetUinhEncoder/轉換/母到音.py
TshetUinhEncoder/轉換/母與等到類.py
TshetUinhEncoder/轉換/韻到攝.py
TshetUinhEncoder/轉換/韻目到韻.py
tshet_uinh_encoder-0.6.0.dist-info/LICENSE
tshet_uinh_encoder-0.6.0.dist-info/METADATA
tshet_uinh_encoder-0.6.0.dist-info/WHEEL
tshet_uinh_encoder-0.6.0.dist-info/top_level.txt
tshet_uinh_encoder-0.6.0.dist-info/RECORD
